decorators/__init__.py
decorators/multithreaded.py
pyRedTools-0.0.1.dist-info/LICENSE
pyRedTools-0.0.1.dist-info/METADATA
pyRedTools-0.0.1.dist-info/WHEEL
pyRedTools-0.0.1.dist-info/top_level.txt
pyRedTools-0.0.1.dist-info/RECORD
